Jtest/__init__.py
Jtest/test.py
JJtest-0.0.1.dist-info/METADATA
JJtest-0.0.1.dist-info/WHEEL
JJtest-0.0.1.dist-info/top_level.txt
JJtest-0.0.1.dist-info/RECORD
