Metadata-Version: 2.1
Name: JJtest
Version: 0.0.1
Summary: just test for learning pipy
Home-page: UNKNOWN
Author: lucq
Author-email: 742820488@qq.com
License: Apache2.0
Platform: UNKNOWN
